nti.recipes.json-1.0.0-py3.6-nspkg.pth
nti/recipes/json/__init__.py
nti/recipes/json/tests/__init__.py
nti/recipes/json/tests/test_recipe.py
nti.recipes.json-1.0.0.dist-info/DESCRIPTION.rst
nti.recipes.json-1.0.0.dist-info/METADATA
nti.recipes.json-1.0.0.dist-info/RECORD
nti.recipes.json-1.0.0.dist-info/WHEEL
nti.recipes.json-1.0.0.dist-info/entry_points.txt
nti.recipes.json-1.0.0.dist-info/metadata.json
nti.recipes.json-1.0.0.dist-info/namespace_packages.txt
nti.recipes.json-1.0.0.dist-info/top_level.txt
nti.recipes.json-1.0.0.dist-info/zip-safe
