Metadata-Version: 2.0
Name: nti.recipes.json
Version: 1.0.0
Summary: zc.buildout recipe that programatically creates JSON files
Home-page: https://github.com/NextThought/nti.recipes.json
Author: Sean Jones
Author-email: sean.jones@nextthought.com
License: Apache
Keywords: buildout json
Platform: UNKNOWN
Classifier: Development Status :: 5 - Production/Stable
Classifier: Intended Audience :: Developers
Classifier: Natural Language :: English
Classifier: Operating System :: OS Independent
Classifier: Programming Language :: Python :: 2
Classifier: Programming Language :: Python :: 2.7
Classifier: Programming Language :: Python :: 3
Classifier: Programming Language :: Python :: 3.6
Classifier: Programming Language :: Python :: Implementation :: CPython
Classifier: Programming Language :: Python :: Implementation :: PyPy
Classifier: Framework :: Buildout
Classifier: License :: OSI Approved :: Apache Software License
Requires-Dist: setuptools
Requires-Dist: zc.buildout
Requires-Dist: zc.recipe.deployment
Provides-Extra: docs
Requires-Dist: Sphinx; extra == 'docs'
Requires-Dist: repoze.sphinx.autointerface; extra == 'docs'
Requires-Dist: sphinx-rtd-theme; extra == 'docs'
Provides-Extra: test
Requires-Dist: pyhamcrest; extra == 'test'
Requires-Dist: zope.testrunner; extra == 'test'
